howe/__init__.py
howe-1.0.4.dist-info/LICENSE.txt
howe-1.0.4.dist-info/METADATA
howe-1.0.4.dist-info/WHEEL
howe-1.0.4.dist-info/top_level.txt
howe-1.0.4.dist-info/RECORD
