Metadata-Version: 2.1
Name: howe
Version: 1.0.4
Summary: Stricter verion of zip.
Author-email: Johannes <johannes-programming@mailfence.com>, Johannes <johannes-horler@posteo.org>
License: The MIT License (MIT)
Project-URL: Documentation, https://pypi.org/project/howe
Project-URL: Download, https://pypi.org/project/howe/#files
Project-URL: Source, https://github.com/johannes-programming/howe
Classifier: License :: OSI Approved :: MIT License
Classifier: Programming Language :: Python
Classifier: Programming Language :: Python :: 3
Classifier: Programming Language :: Python :: 3 :: Only
Requires-Python: >=3.11
License-File: LICENSE.txt
